MicroQuote/VAS_receiver.cp37-win32.pyd
MicroQuote/__init__.py
MicroQuote/sql.cp37-win32.pyd
MicroQuote-0.9.59.dist-info/METADATA
MicroQuote-0.9.59.dist-info/WHEEL
MicroQuote-0.9.59.dist-info/top_level.txt
MicroQuote-0.9.59.dist-info/RECORD
