Metadata-Version: 2.1
Name: MicroQuote
Version: 0.9.59
Summary: MicroQuote for Windows
Home-page: UNKNOWN
Author: haohaninfo
Author-email: haohanservice@haohaninfo.com
License: UNKNOWN
Platform: UNKNOWN
Classifier: Programming Language :: Python :: 3.7
Classifier: Operating System :: Microsoft :: Windows
Requires-Dist: pika (>=1.0.0)
Requires-Dist: requests
